hello.py
svlearn_sonu-0.1.1.dist-info/METADATA
svlearn_sonu-0.1.1.dist-info/WHEEL
svlearn_sonu-0.1.1.dist-info/top_level.txt
svlearn_sonu-0.1.1.dist-info/RECORD
